fuggle/__init__.py
fuggle/_utils.py
fuggle/execution_engine.py
fuggle/outputters.py
fuggle_version/__init__.py
tests/__init__.py
tests/test_execution_engine.py
tests/test_outputters.py
tests/test_utils.py
fuggle-0.3.3.dist-info/LICENSE
fuggle-0.3.3.dist-info/METADATA
fuggle-0.3.3.dist-info/WHEEL
fuggle-0.3.3.dist-info/top_level.txt
fuggle-0.3.3.dist-info/RECORD
