Metadata-Version: 2.1
Name: fuggle
Version: 0.3.3
Summary: Fugue for Kaggle users
Home-page: http://github.com/fugue-project/fuggle
Author: Han Wang
Author-email: goodwanghan@gmail.com
License: Apache-2.0
Keywords: fugue kaggle sql spark dask pandas
Platform: UNKNOWN
Classifier: Development Status :: 5 - Production/Stable
Classifier: Intended Audience :: Developers
Classifier: Topic :: Software Development :: Libraries :: Python Modules
Classifier: License :: OSI Approved :: Apache Software License
Classifier: Programming Language :: Python :: 3.6
Classifier: Programming Language :: Python :: 3.7
Classifier: Programming Language :: Python :: 3.8
Classifier: Programming Language :: Python :: 3 :: Only
Requires-Python: >=3.6
Requires-Dist: fugue[dask,spark,sql] (==0.6.3)
Requires-Dist: tune[all] (==0.0.9.dev1)
Requires-Dist: notebook
Requires-Dist: kaggle
Requires-Dist: seaborn
Requires-Dist: qpd
Requires-Dist: dask[dataframe]
Requires-Dist: pandavro
Requires-Dist: psutil
Provides-Extra: blazing
Requires-Dist: fugue-blazing (==0.0.3) ; extra == 'blazing'
Provides-Extra: dasksql
Requires-Dist: dask-sql (!=0.3.4) ; extra == 'dasksql'
